xy_request_handler_web/Web.py
xy_request_handler_web/__init__.py
xy_request_handler_web-1.0.0.dist-info/LICENSE
xy_request_handler_web-1.0.0.dist-info/METADATA
xy_request_handler_web-1.0.0.dist-info/WHEEL
xy_request_handler_web-1.0.0.dist-info/top_level.txt
xy_request_handler_web-1.0.0.dist-info/RECORD
